{
    "regions": [
        {
            "boundingBox": {
                "width": 500, 
                "top": 0, 
                "left": 0, 
                "height": 500
            }, 
            "points": [
                {
                    "y": 0, 
                    "x": 0
                }, 
                {
                    "y": 0, 
                    "x": 500
                }, 
                {
                    "y": 500, 
                    "x": 500
                }, 
                {
                    "y": 500, 
                    "x": 0
                }
            ], 
            "type": "RECTANGLE", 
            "id": "7rn5u0Sne", 
            "tags": [
                "pancake"
            ]
        }
    ], 
    "version": "2.2.0", 
    "asset": {
        "name": "img_51.jpg", 
        "format": "jpg", 
        "state": 2, 
        "path": "file:/Users/amako/Documents/Python/apps/bing/cake/img_51.jpg", 
        "type": 1, 
        "id": "iv492Zf2hendfgJBXyGnZ2814BkVEkIn", 
        "size": {
            "width": 500, 
            "height": 500
        }
    }
}